PipeLibrary/__init__.py
robotframework_pipe-0.1.2.dist-info/LICENSE
robotframework_pipe-0.1.2.dist-info/METADATA
robotframework_pipe-0.1.2.dist-info/WHEEL
robotframework_pipe-0.1.2.dist-info/RECORD
