Metadata-Version: 2.1
Name: robotframework-pipe
Version: 0.1.2
Summary: Enhance Robot Framework with functional-style keyword chaining. Streamline test cases by piping output of one keyword as input to another, simplifying data flow and readability.
Home-page: https://github.com/touchedthecode/robotframework-pipe
License: Apache-2.0
Author: touchedthecode
Author-email: git@touchedthecode.com
Requires-Python: >=3.8,<4.0
Classifier: License :: OSI Approved :: Apache Software License
Classifier: Programming Language :: Python :: 3
Classifier: Programming Language :: Python :: 3.8
Classifier: Programming Language :: Python :: 3.9
Classifier: Programming Language :: Python :: 3.10
Classifier: Programming Language :: Python :: 3.11
Classifier: Programming Language :: Python :: 3.12
Requires-Dist: robotframework (>5.0.1)
Project-URL: Repository, https://github.com/touchedthecode/robotframework-pipe
